melishield/__init__.py
melishield-0.1.4.dist-info/licenses/LICENSE
melishield-0.1.4.dist-info/METADATA
melishield-0.1.4.dist-info/WHEEL
melishield-0.1.4.dist-info/top_level.txt
melishield-0.1.4.dist-info/RECORD
